djfritz/__init__.py
djfritz/apps.py
djfritz/context_processors.py
djfritz/fritz_connection.py
djfritz/permissions.py
djfritz/signals.py
djfritz/admin/__init__.py
djfritz/admin/hosts.py
djfritz/admin/hosts_groups.py
djfritz/admin_views/__init__.py
djfritz/admin_views/base_views.py
djfritz/admin_views/diagnose.py
djfritz/admin_views/group_management.py
djfritz/admin_views/host_infomation.py
djfritz/locale/de/LC_MESSAGES/django.mo
djfritz/locale/de/LC_MESSAGES/django.po
djfritz/locale/en/LC_MESSAGES/django.mo
djfritz/locale/en/LC_MESSAGES/django.po
djfritz/management/__init__.py
djfritz/management/commands/__init__.py
djfritz/management/commands/update_hosts.py
djfritz/migrations/0001_add_host_model.py
djfritz/migrations/0002_hostmodel_ip_v4_hostmodel_ip_v6.py
djfritz/migrations/0003_hostmodel_wan_access.py
djfritz/migrations/0004_host_group.py
djfritz/migrations/0005_alter_hostmodel_group.py
djfritz/migrations/__init__.py
djfritz/models/__init__.py
djfritz/models/base.py
djfritz/models/hosts.py
djfritz/models/hosts_groups.py
djfritz/services/__init__.py
djfritz/services/hosts.py
djfritz/templates/admin/djfritz/hostmodel/change_form_object_tools.html
djfritz/templates/admin/djfritz/hostmodel/change_list.html
djfritz/templates/admin/djfritz/hostmodel/column_verbose_name.html
djfritz/templates/djfritz/diagnose_connection.html
djfritz/templates/djfritz/group_management.html
djfritz/templates/djfritz/host_information.html
djfritz/templates/djfritz/host_name_info.html
djfritz/templates/djfritz/last_connect_info.html
djfritz/templates/djfritz/list_box_services.html
djfritz/templates/djfritz/mesh_topology.html
djfritz/templates/djfritz/includes/dynamic_view_menu.html
djfritz/templates/djfritz/includes/fritzbox_link.html
djfritz/templatetags/__init__.py
djfritz/templatetags/djfritz.py
djfritz/tests/__init__.py
djfritz/tests/fixtures/__init__.py
djfritz/tests/fixtures/users.py
djfritz_project/__init__.py
djfritz_project/__main__.py
djfritz_project/middlewares.py
django_fritzconnection-0.4.0.dist-info/AUTHORS
django_fritzconnection-0.4.0.dist-info/LICENSE
django_fritzconnection-0.4.0.dist-info/METADATA
django_fritzconnection-0.4.0.dist-info/WHEEL
django_fritzconnection-0.4.0.dist-info/entry_points.txt
django_fritzconnection-0.4.0.dist-info/top_level.txt
django_fritzconnection-0.4.0.dist-info/RECORD
