Metadata-Version: 2.1
Name: django-fritzconnection
Version: 0.4.0
Summary: Web based FritzBox management using Python/Django.
Author-email: Jens Diemer <django-fritzconnection@jensdiemer.de>
License: GPL-3.0-or-later
Project-URL: Documentation, https://github.com/jedie/django-fritzconnection
Project-URL: Source, https://github.com/jedie/django-fritzconnection
Requires-Python: >=3.11
License-File: LICENSE
License-File: AUTHORS
Requires-Dist: django
Requires-Dist: fritzconnection
Requires-Dist: django-reversion-compare
Requires-Dist: django-tagulous
Requires-Dist: django-admin-sortable2
Requires-Dist: colorlog
Requires-Dist: gunicorn
Requires-Dist: bx-py-utils
Requires-Dist: bx-django-utils
Provides-Extra: dev
Requires-Dist: cmd2-ext-test ; extra == 'dev'
Requires-Dist: beautifulsoup4 ; extra == 'dev'
Requires-Dist: django-debug-toolbar ; extra == 'dev'
Requires-Dist: manage-django-project ; extra == 'dev'
Requires-Dist: tblib ; extra == 'dev'
Requires-Dist: pip-tools ; extra == 'dev'
Requires-Dist: tox ; extra == 'dev'
Requires-Dist: coverage ; extra == 'dev'
Requires-Dist: autopep8 ; extra == 'dev'
Requires-Dist: pyupgrade ; extra == 'dev'
Requires-Dist: flake8 ; extra == 'dev'
Requires-Dist: flake8-bugbear ; extra == 'dev'
Requires-Dist: pyflakes ; extra == 'dev'
Requires-Dist: codespell ; extra == 'dev'
Requires-Dist: EditorConfig ; extra == 'dev'
Requires-Dist: pip-audit ; extra == 'dev'
Requires-Dist: mypy ; extra == 'dev'
Requires-Dist: twine ; extra == 'dev'
Requires-Dist: typeguard ; extra == 'dev'
Requires-Dist: pre-commit ; extra == 'dev'
Requires-Dist: darker[color,flynt,isort] ; extra == 'dev'
Requires-Dist: model-bakery ; extra == 'dev'
Requires-Dist: requests-mock ; extra == 'dev'
Requires-Dist: django-override-storage ; extra == 'dev'
Requires-Dist: backports.tarfile ; extra == 'dev'
